{
  "basePath": "/2010-04-01/Accounts/ACXXXXXXXXXXXXXXXXXXXXXXXXXXXXXXXX",
  "paths": {
    "": {
      "POST": {
        "parameters": [
          {
            "in": "query",
            "name": "Only return Account resources with the given status. Can be closed , suspended or active .",
            "description": "Only return Account resources with the given status. Can be closed , suspended or active .",
            "type": "integer",
            "required": "required"
          }
        ]
      },
      "get": {
        "parameters": [
          {
            "in": "query",
            "name": "Status",
            "description": "Alter the status of this account: use closed to irreversibly close this account, suspended to temporarily suspend it, or active to reactivate it.",
            "type": "integer",
            "required": "required"
          }
        ]
      }
    },
    "/AvailablePhoneNumbers/GB/Mo": {
      "GET": {
        "parameters": [
          {
            "in": "query",
            "name": "Beta",
            "description": "If true , only include countries where phone numbers new to the Twilio platform are available. If false , do not include new inventory.",
            "type": "integer",
            "required": "required"
          }
        ]
      }
    },
    "/OutgoingCallerIds": {
      "get": {
        "parameters": [
          {
            "in": "query",
            "name": "PhoneNumber",
            "description": "The phone number to verify. Should be formatted with a '+' and country code e.g., +16175551212 ( E.164 format). Twilio will also accept unformatted US numbers e.g., (415) 555-1212, 415-555-1212.",
            "type": "integer",
            "required": "required"
          }
        ]
      }
    },
    "/Calls/CAe03b7cd806070d1f32b": {
      "POST": {
        "parameters": [
          {
            "in": "query",
            "name": "AccountSid",
            "description": "Your Twilio account id. It is 34 characters long, and always starts with the letters AC.",
            "type": "integer",
            "required": "required"
          },
          {
            "in": "query",
            "name": "FeedbackSummarySid",
            "description": "The unique id of the Feedback Summary.",
            "type": "integer",
            "required": "required"
          },
          {
            "in": "query",
            "name": "Status",
            "description": "The status of the Feedback Summary; queued, in-progress, completed, or failed.",
            "type": "integer",
            "required": "required"
          },
          {
            "in": "query",
            "name": "ResourceUri",
            "description": "The Feedback Summary Resource URI.",
            "type": "integer",
            "required": "required"
          }
        ]
      },
      "put": {
        "parameters": [
          {
            "in": "query",
            "name": "Issue",
            "description": "One or more issues experienced during the call. The issues can be: imperfect-audio , dropped-call , incorrect-caller-id , post-dial-delay , digits-not-captured , audio-latency , or one-way-audio .",
            "type": "integer",
            "required": "required"
          }
        ]
      }
    },
    "/Messages": {
      "POST": {
        "parameters": [
          {
            "in": "query",
            "name": "MessageStatus",
            "description": "The status of the message. Message delivery information is reflected in message status. The possible values are described here .",
            "type": "integer",
            "required": "required"
          },
          {
            "in": "query",
            "name": "ErrorCode",
            "description": "The error code (if any) associated with your message. If your message status is failed or undelivered , the ErrorCode can give you more information about the failure. If the message was delivered successfully, no ErrorCode will be present. The possible values are described here .",
            "type": "integer",
            "required": "required"
          }
        ]
      }
    },
    "/Applications": {
      "put": {
        "parameters": []
      }
    },
    "https://preview.twilio.com/porting/Loas/PX800f449d0399ed014aae2bcc0cc2f2ec": {
      "POST": {
        "parameters": [
          {
            "in": "query",
            "name": "status",
            "description": "Only retrieve the list of port orders in this state. Possible values: 1. Created, 2. Received, 3. Submitting, 4. Submitted, 5. Delivered, 6. Completed, 7. Canceled, 8. Rejected, 9. Failed",
            "type": "integer",
            "required": "required"
          },
          {
            "in": "query",
            "name": "activation_date",
            "description": "Only retrieve the list of port orders comprising phone numbers that are scheduled to become active on a particular date, in GMT RFC 2822 format, e.g., activation_date=2009-07-06. Inequality can also be specified to retrieve the list of port orders comprising phone numbers that are scheduled to become active on or before midnight on a particular date, e.g. activation_date<=2009-07-06, or to retrieve the list of port orders comprising phone numbers that are scheduled to become active on or after midnight on a particular date, e.g. activation_date>=2009-07-06.",
            "type": "integer",
            "required": "required"
          },
          {
            "in": "query",
            "name": "friendly_name",
            "description": "Only retrieve the list of port orders with this friendly name.",
            "type": "integer",
            "required": "required"
          },
          {
            "in": "query",
            "name": "date_created",
            "description": "Only retrieve the list of port orders that were created on a particular date, in GMT RFC 2822 format, e.g., date_created=2009-07-06. Inequality can be specified to retrieve the list of port orders that were created before or after a particular date as well.",
            "type": "integer",
            "required": "required"
          },
          {
            "in": "query",
            "name": "number",
            "description": "Only retrieve the list of port orders that comprise this porting phone number. This must be in E.164 format, e.g., +16175551212.",
            "type": "integer",
            "required": "required"
          },
          {
            "in": "query",
            "name": "before_sid",
            "description": "Only retrieve port orders before the port order with this SID in the list of all port orders.",
            "type": "integer",
            "required": "required"
          },
          {
            "in": "query",
            "name": "after_sid",
            "description": "Only retrieve port orders after the port order with this SID in the list of all port orders.",
            "type": "integer",
            "required": "required"
          }
        ]
      }
    },
    "/Applications/AP2a0747eba6ab": {
      "POST": {
        "parameters": []
      },
      "put": {
        "parameters": [
          {
            "in": "query",
            "name": "ApiVersion",
            "description": "Requests to this application's URLs will start a new TwiML session with this API version. Either 2010-04-01 or 2008-08-01 .",
            "type": "integer",
            "required": "required"
          },
          {
            "in": "query",
            "name": "VoiceUrl",
            "description": "The URL that Twilio should request when somebody dials a phone number assigned to this application.",
            "type": "integer",
            "required": "required"
          },
          {
            "in": "query",
            "name": "VoiceMethod",
            "description": "The HTTP method that should be used to request the VoiceUrl . Either GET or POST .",
            "type": "integer",
            "required": "required"
          },
          {
            "in": "query",
            "name": "VoiceFallbackUrl",
            "description": "A URL that Twilio will request if an error occurs requesting or executing the TwiML defined by VoiceUrl .",
            "type": "integer",
            "required": "required"
          },
          {
            "in": "query",
            "name": "VoiceFallbackMethod",
            "description": "The HTTP method that should be used to request the VoiceFallbackUrl . Either GET or POST .",
            "type": "integer",
            "required": "required"
          },
          {
            "in": "query",
            "name": "StatusCallback",
            "description": "The URL that Twilio will request to pass status parameters (such as call ended) to your application.",
            "type": "integer",
            "required": "required"
          },
          {
            "in": "query",
            "name": "StatusCallbackMethod",
            "description": "The HTTP method Twilio will use to make requests to the StatusCallback URL. Either GET or POST .",
            "type": "integer",
            "required": "required"
          },
          {
            "in": "query",
            "name": "VoiceCallerIdLookup",
            "description": "Do a lookup of a caller's name from the CNAM database and post it to your app. Either true or false .",
            "type": "integer",
            "required": "required"
          },
          {
            "in": "query",
            "name": "SmsUrl",
            "description": "The URL that Twilio should request when somebody sends an SMS to a phone number assigned to this application.",
            "type": "integer",
            "required": "required"
          },
          {
            "in": "query",
            "name": "SmsMethod",
            "description": "The HTTP method that should be used to request the SmsUrl . Either GET or POST .",
            "type": "integer",
            "required": "required"
          },
          {
            "in": "query",
            "name": "SmsFallbackUrl",
            "description": "A URL that Twilio will request if an error occurs requesting or executing the TwiML defined by SmsUrl .",
            "type": "integer",
            "required": "required"
          },
          {
            "in": "query",
            "name": "SmsFallbackMethod",
            "description": "The HTTP method that should be used to request the SmsFallbackUrl . Either GET or POST .",
            "type": "integer",
            "required": "required"
          },
          {
            "in": "query",
            "name": "SmsStatusCallback",
            "description": "The URL that Twilio will POST to when a message is sent via the /SMS/Messages endpoint if you specify the Sid of this application on an outgoing SMS request .",
            "type": "integer",
            "required": "required"
          },
          {
            "in": "query",
            "name": "MessageStatusCallback",
            "description": "Twilio will make a POST request to this URL to pass status parameters (such as sent or failed) to your application if you use the /Messages endpoint to send the message and specify this application's Sid as the ApplicationSid on an outgoing SMS request .",
            "type": "integer",
            "required": "required"
          }
        ]
      }
    },
    "/Queues": {
      "get": {
        "parameters": [
          {
            "in": "query",
            "name": "MaxSize",
            "description": "The maximum size of this queue. The default is 100. The maximum is 1000.",
            "type": "integer",
            "required": "required"
          }
        ]
      }
    },
    "/OutgoingCallerIds/PNe536d32": {
      "DELETE": {
        "parameters": [
          {
            "in": "query",
            "name": "PhoneNumber",
            "description": "Only show the caller id resource that exactly matches this phone number.",
            "type": "integer",
            "required": "required"
          },
          {
            "in": "query",
            "name": "FriendlyName",
            "description": "Only show the caller id resource that exactly matches this name.",
            "type": "integer",
            "required": "required"
          }
        ]
      }
    },
    "/SMS/Messages/SM800f449d0399": {
      "put": {
        "parameters": [
          {
            "in": "query",
            "name": "To",
            "description": "Only show SMS messages to this phone number.",
            "type": "integer",
            "required": "required"
          },
          {
            "in": "query",
            "name": "From",
            "description": "Only show SMS messages from this phone number.",
            "type": "integer",
            "required": "required"
          },
          {
            "in": "query",
            "name": "DateSent",
            "description": "Only show SMS messages sent on this date (in GMT format), given as YYYY-MM-DD . Example: DateSent=2009-07-06 . You can also specify inequality, such as DateSent<=YYYY-MM-DD for SMS messages that were sent on or before midnight on a date, and DateSent>=YYYY-MM-DD for SMS messages sent on or after midnight on a date.",
            "type": "integer",
            "required": "required"
          }
        ]
      }
    },
    "/IncomingPhoneNumbers": {
      "POST": {
        "parameters": [
          {
            "in": "query",
            "name": "PhoneNumber",
            "description": "The phone number you want to purchase. The number should be formatted starting with a '+' followed by the country code and the number in E.164 format e.g., '+15105555555'. You must include this to have your POST succeed.",
            "type": "integer",
            "required": "required"
          }
        ]
      },
      "get": {
        "parameters": [
          {
            "in": "query",
            "name": "VoiceUrl",
            "description": "The URL that Twilio should request when somebody dials the new phone number. The VoiceURL will no longer be used if a VoiceApplicationSid or a TrunkSid is set.",
            "type": "integer",
            "required": "required"
          },
          {
            "in": "query",
            "name": "VoiceMethod",
            "description": "The HTTP method that should be used to request the VoiceUrl . Must be either GET or POST . Defaults to POST .",
            "type": "integer",
            "required": "required"
          },
          {
            "in": "query",
            "name": "VoiceFallbackUrl",
            "description": "A URL that Twilio will request if an error occurs requesting or executing the TwiML at Url .",
            "type": "integer",
            "required": "required"
          },
          {
            "in": "query",
            "name": "VoiceFallbackMethod",
            "description": "The HTTP method that should be used to request the VoiceFallbackUrl . Either GET or POST . Defaults to POST .",
            "type": "integer",
            "required": "required"
          },
          {
            "in": "query",
            "name": "StatusCallback",
            "description": "The URL that Twilio will request to pass status parameters (such as call ended) to your application.",
            "type": "integer",
            "required": "required"
          },
          {
            "in": "query",
            "name": "StatusCallbackMethod",
            "description": "The HTTP method Twilio will use to make requests to the StatusCallback URL. Either GET or POST . Defaults to POST .",
            "type": "integer",
            "required": "required"
          },
          {
            "in": "query",
            "name": "VoiceCallerIdLookup",
            "description": "Do a lookup of a caller's name from the CNAM database and post it to your app. Either true or false . Defaults to false .",
            "type": "integer",
            "required": "required"
          },
          {
            "in": "query",
            "name": "VoiceApplicationSid",
            "description": "The 34 character sid of the application Twilio should use to handle phone calls to the new number. If a VoiceApplicationSid is present, Twilio will ignore all of the voice urls above and use those set on the application. Setting a VoiceApplicationSid will automatically delete your TrunkSid and vice versa.",
            "type": "integer",
            "required": "required"
          },
          {
            "in": "query",
            "name": "TrunkSid",
            "description": "The 34 character sid of the Trunk Twilio should use to handle phone calls to this number. If a TrunkSid is present, Twilio will ignore all of the voice urls and voice applications above and use those set on the Trunk. Setting a TrunkSid will automatically delete your VoiceApplicationSid and vice versa.",
            "type": "integer",
            "required": "required"
          },
          {
            "in": "query",
            "name": "SmsUrl",
            "description": "The URL that Twilio should request when somebody sends an SMS to the phone number.",
            "type": "integer",
            "required": "required"
          },
          {
            "in": "query",
            "name": "SmsMethod",
            "description": "The HTTP method that should be used to request the SmsUrl . Must be either GET or POST . Defaults to POST .",
            "type": "integer",
            "required": "required"
          },
          {
            "in": "query",
            "name": "SmsFallbackUrl",
            "description": "A URL that Twilio will request if an error occurs requesting or executing the TwiML defined by SmsUrl .",
            "type": "integer",
            "required": "required"
          },
          {
            "in": "query",
            "name": "SmsFallbackMethod",
            "description": "The HTTP method that should be used to request the SmsFallbackUrl . Must be either GET or POST . Defaults to POST .",
            "type": "integer",
            "required": "required"
          },
          {
            "in": "query",
            "name": "SmsApplicationSid",
            "description": "The 34 character sid of the application Twilio should use to handle SMSs sent to the new number. If a SmsApplicationSid is present, Twilio will ignore all of the SMS urls above and use those set on the application.",
            "type": "integer",
            "required": "required"
          },
          {
            "in": "query",
            "name": "ApiVersion",
            "description": "The Twilio REST API version to use for incoming calls made to this number. If omitted, uses 2010-04-01 .",
            "type": "integer",
            "required": "required"
          }
        ]
      }
    },
    "/Usage/Triggers": {
      "POST": {
        "parameters": [
          {
            "in": "query",
            "name": "AccountSid",
            "description": "Your Twilio account id. It is 34 characters long, and always starts with the letters AC.",
            "type": "integer",
            "required": "required"
          },
          {
            "in": "query",
            "name": "UsageTriggerSid",
            "description": "The unique identifier of the UsageTrigger that fired.",
            "type": "integer",
            "required": "required"
          },
          {
            "in": "query",
            "name": "DateFired",
            "description": "When the UsageTrigger fired, in GMT.",
            "type": "integer",
            "required": "required"
          },
          {
            "in": "query",
            "name": "Recurring",
            "description": "How the UsageTrigger that fired recurs. Empty for non-recurring UsageTriggers. One of daily , monthly , or yearly for recurring UsageTriggers.",
            "type": "integer",
            "required": "required"
          },
          {
            "in": "query",
            "name": "UsageCategory",
            "description": "The usage category the UsageTrigger watches. One of the supported usage categories .",
            "type": "integer",
            "required": "required"
          },
          {
            "in": "query",
            "name": "TriggerBy",
            "description": "The field in the UsageRecord that fires the UsageTrigger. One of count , usage , or price as described in the UsageRecords documentation .",
            "type": "integer",
            "required": "required"
          },
          {
            "in": "query",
            "name": "TriggerValue",
            "description": "The value at which the UsageTrigger will fire.",
            "type": "integer",
            "required": "required"
          },
          {
            "in": "query",
            "name": "CurrentUsageValue",
            "description": "The current value of the usage the UsageTrigger is watching.",
            "type": "integer",
            "required": "required"
          },
          {
            "in": "query",
            "name": "UsageRecordUri",
            "description": "The URI of the UsageRecord this UsageTrigger was watching when it fired.",
            "type": "integer",
            "required": "required"
          },
          {
            "in": "query",
            "name": "IdempotencyToken",
            "description": "A random token generated by Twilio, and guaranteed to be unique for this particular firing of this UsageTrigger. See Best Practices with Usage Trigger Callbacks .",
            "type": "integer",
            "required": "required"
          }
        ]
      },
      "geT": {
        "parameters": [
          {
            "in": "query",
            "name": "TriggerBy",
            "description": "The field in the UsageRecord that will fire the trigger. One of count , usage , or price as described in the UsageRecords documentation . The default is usage .",
            "type": "integer",
            "required": "required"
          },
          {
            "in": "query",
            "name": "Recurring",
            "description": "To make a recurring trigger that counts over its recurring interval, set this to one of: daily , monthly , or yearly . Omit this to create a non-recurring trigger.",
            "type": "integer",
            "required": "required"
          },
          {
            "in": "query",
            "name": "CallbackMethod",
            "description": "Twilio will use this HTTP method when making a request to the CallbackUrl. GET or POST . The default is POST .",
            "type": "integer",
            "required": "required"
          }
        ]
      }
    },
    "/SIP/Domains/SD32a3c49700934": {
      "POST": {},
      "put": {
        "parameters": [
          {
            "in": "query",
            "name": "IpAccessControlListSid",
            "description": "The Sid of the IpAccessControlList that you want to associated with this domain. Once associated, Twilio will start authenticating access to the domain against this list.",
            "type": "integer",
            "required": "required"
          }
        ]
      }
    },
    "/Conferences/CFbbe46ff1274e2": {
      "get": {
        "parameters": [
          {
            "in": "query",
            "name": "Status",
            "description": "Specifying completed will end the conference and kick all participants",
            "type": "integer",
            "required": "required"
          }
        ]
      }
    },
    "/Recordings/RE557ce644e5ab84": {
      "DELETE": {
        "parameters": [
          {
            "in": "query",
            "name": "CallSid",
            "description": "Show only recordings made during the call given by this sid.",
            "type": "integer",
            "required": "required"
          },
          {
            "in": "query",
            "name": "DateCreated",
            "description": "Only show recordings created on the given date. Should be formatted as YYYY-MM-DD . You can also specify inequality, such as DateCreated<=YYYY-MM-DD for recordings generated at or before midnight on a date, and DateCreated>=YYYY-MM-DD for recordings generated at or after midnight on a date.",
            "type": "integer",
            "required": "required"
          }
        ]
      }
    },
    "/SIP/IpAccessControlLists/AL": {
      "POST": {},
      "get": {
        "parameters": [
          {
            "in": "query",
            "name": "IpAddress",
            "description": "An IP address in dotted decimal notation from which you want to accept traffic. Any SIP requests from this IP address will be allowed by Twilio. IPv4 only supported today.",
            "type": "integer",
            "required": "required"
          }
        ]
      }
    },
    "/Queues/QU5ef8732a3c49700934": {
      "POST": {}
    },
    "/OutgoingCallerIds/PNe905d7e": {
      "get": {
        "parameters": []
      }
    },
    "https://api.twilio.com/2010-04-01/Accounts/{TestAccountSid}/IncomingPhoneNumbers": {
      "POST": {}
    },
    "https://api.twilio.com/2010-04-01/Accounts/AC25e16e9a716a4a1786a7c83f58e30482/Conferences/CF1446ceacaefdc": {
      "POST": {
        "parameters": [
          {
            "in": "query",
            "name": "Status",
            "description": "Only show conferences currently in with this status. May be in-progress , or completed .",
            "type": "integer",
            "required": "required"
          },
          {
            "in": "query",
            "name": "FriendlyName",
            "description": "List conferences whose FriendlyName exactly matches this string.",
            "type": "integer",
            "required": "required"
          },
          {
            "in": "query",
            "name": "DateCreated",
            "description": "Only show conferences that started on this date, given as YYYY-MM-DD . You can also specify inequality, such as DateCreated<=YYYY-MM-DD for conferences that started at or before midnight on a date, and DateCreated>=YYYY-MM-DD for conferences that started at or after midnight on a date.",
            "type": "integer",
            "required": "required"
          },
          {
            "in": "query",
            "name": "DateUpdated",
            "description": "Only show conferences that were last updated on this date, given as YYYY-MM-DD . You can also specify inequality, such as DateUpdated<=YYYY-MM-DD for conferences that were last updated at or before midnight on a date, and DateUpdated>=YYYY-MM-DD for conferences that were updated at or after midnight on a date.",
            "type": "integer",
            "required": "required"
          }
        ]
      }
    },
    "/SMS/ShortCodes/SC6b20cb705c": {
      "POST": {
        "parameters": [
          {
            "in": "query",
            "name": "ShortCode",
            "description": "Only show the ShortCode resources that match this pattern. You can specify partial numbers and use '*' as a wildcard for any digit.",
            "type": "integer",
            "required": "required"
          },
          {
            "in": "query",
            "name": "FriendlyName",
            "description": "Only show the ShortCode resources with friendly names that exactly match this name.",
            "type": "integer",
            "required": "required"
          }
        ]
      },
      "get": {
        "parameters": [
          {
            "in": "query",
            "name": "ApiVersion",
            "description": "SMSs to this short code will start a new TwiML session with this API version. Either 2010-04-01 or 2008-08-01 .",
            "type": "integer",
            "required": "required"
          },
          {
            "in": "query",
            "name": "SmsUrl",
            "description": "The URL that Twilio should request when somebody sends an SMS to the short code.",
            "type": "integer",
            "required": "required"
          },
          {
            "in": "query",
            "name": "SmsMethod",
            "description": "The HTTP method that should be used to request the SmsUrl . Either GET or POST .",
            "type": "integer",
            "required": "required"
          },
          {
            "in": "query",
            "name": "SmsFallbackUrl",
            "description": "A URL that Twilio will request if an error occurs requesting or executing the TwiML at the SmsUrl .",
            "type": "integer",
            "required": "required"
          },
          {
            "in": "query",
            "name": "SmsFallbackMethod",
            "description": "The HTTP method that should be used to request the SmsFallbackUrl . Either GET or POST .",
            "type": "integer",
            "required": "required"
          }
        ]
      }
    },
    "https://www.mycompany.com/connect_authorize\"": {
      "put": {
        "parameters": [
          {
            "in": "query",
            "name": "AuthorizeRedirectUrl",
            "description": "The URL the user's browser will redirect to after Twilio authenticates the user and obtains authorization for this Connect App.",
            "type": "integer",
            "required": "required"
          },
          {
            "in": "query",
            "name": "DeauthorizeCallbackUrl",
            "description": "The URL to which Twilio will send a request when a user de-authorizes this Connect App.",
            "type": "integer",
            "required": "required"
          },
          {
            "in": "query",
            "name": "DeauthorizeCallbackMethod",
            "description": "The HTTP method to be used when making a request to the DeauthorizeCallbackUrl . Either GET or POST .",
            "type": "integer",
            "required": "required"
          },
          {
            "in": "query",
            "name": "Permissions",
            "description": "A comma-separated list of permssions you will request from users of this ConnectApp. Valid permssions are get-all or post-all .",
            "type": "integer",
            "required": "required"
          },
          {
            "in": "query",
            "name": "Description",
            "description": "A more detailed human readable description of the Connect App.",
            "type": "integer",
            "required": "required"
          },
          {
            "in": "query",
            "name": "CompanyName",
            "description": "The company name for this Connect App.",
            "type": "integer",
            "required": "required"
          },
          {
            "in": "query",
            "name": "HomepageUrl",
            "description": "The public URL where users can obtain more information about this Connect App.",
            "type": "integer",
            "required": "required"
          }
        ]
      }
    },
    "https://preview.twilio.com/porting/PortOrders": {
      "GET": {
        "parameters": [
          {
            "in": "query",
            "name": "company_name",
            "description": "Name of the company that owns the porting phone number. Please note that this is the name we will use to populate the “Business Name” field in the LOA associated with this port request.",
            "type": "integer",
            "required": "required"
          },
          {
            "in": "query",
            "name": "billing_phone_number",
            "description": "The main billing phone number on the account (with your current provider/carrier) that is associated with the porting phone number in this port request. This must be in E.164 format, e.g., +16175551212.",
            "type": "integer",
            "required": "required"
          },
          {
            "in": "query",
            "name": "account_number",
            "description": "Account number of the account (with your current provider/carrier) that is associated with the porting phone number in this port request. This is mandatory for Wireless numbers but optional for Landline and Toll Free numbers.",
            "type": "integer",
            "required": "required"
          },
          {
            "in": "query",
            "name": "pin_number",
            "description": "PIN number of the account (with your current provider/carrier) that is associated with the porting phone number in this port request. This is mandatory for Wireless numbers but optional for Landline and Toll Free numbers.",
            "type": "integer",
            "required": "required"
          },
          {
            "in": "query",
            "name": "ssn_last_four",
            "description": "Last four digits of the social security number of the person that owns the porting phone number. Please note that this person must be the one who is authorized to and will sign the LOA. This is mandatory for Wireless numbers but optional for Landline and Toll Free numbers.",
            "type": "integer",
            "required": "required"
          },
          {
            "in": "query",
            "name": "current_carrier",
            "description": "Name of the current provider/carrier of the porting phone number.",
            "type": "integer",
            "required": "required"
          },
          {
            "in": "query",
            "name": "activation_date",
            "description": "Desired Firm Order Commitment (FOC) date and time, given as GMT RFC 2822 format – i.e., the date and time at which the number will port. This will be overridden if the earliest possible FOC date is on a later date.",
            "type": "integer",
            "required": "required"
          },
          {
            "in": "query",
            "name": "status_callback",
            "description": "The URL that Twilio will POST to each time the port request status changes to one of Delivered, Failed, or Completed.",
            "type": "integer",
            "required": "required"
          },
          {
            "in": "query",
            "name": "cc_emails",
            "description": "Array of email address(es) of the person/people whom Twilio should notify each time the port request status changes to one of Delivered, Failed, or Completed.",
            "type": "integer",
            "required": "required"
          }
        ]
      }
    },
    "/Calls/CA42ed11f93dc08b95202": {
      "get": {
        "parameters": [
          {
            "in": "query",
            "name": "To",
            "description": "Only show calls to this phone number or Client identifier.",
            "type": "integer",
            "required": "required"
          },
          {
            "in": "query",
            "name": "From",
            "description": "Only show calls from this phone number or Client identifier.",
            "type": "integer",
            "required": "required"
          },
          {
            "in": "query",
            "name": "Status",
            "description": "Only show calls currently in this status. May be queued , ringing , in-progress , canceled , completed , failed , busy , or no-answer .",
            "type": "integer",
            "required": "required"
          },
          {
            "in": "query",
            "name": "StartTime",
            "description": "Only show calls that started on this date, given as YYYY-MM-DD . Also supports inequalities, such as StartTime<=YYYY-MM-DD for calls that started at or before midnight on a date, and StartTime>=YYYY-MM-DD for calls that started at or after midnight on a date.",
            "type": "integer",
            "required": "required"
          },
          {
            "in": "query",
            "name": "ParentCallSid",
            "description": "Only show calls spawned by the call with this Sid.",
            "type": "integer",
            "required": "required"
          }
        ]
      }
    },
    "https://www.example.com/monthly-usage-trigger\"": {
      "POST": {
        "parameters": [
          {
            "in": "query",
            "name": "Recurring",
            "description": "Only show UsageTriggers that count over this interval. One of daily , monthly , or yearly . To retrieve non-recurring triggers, leave this empty or use alltime .",
            "type": "integer",
            "required": "required"
          },
          {
            "in": "query",
            "name": "UsageCategory",
            "description": "Only show UsageTriggers that watch this usage category. Must be one of the supported usage categories .",
            "type": "integer",
            "required": "required"
          },
          {
            "in": "query",
            "name": "TriggerBy",
            "description": "Only show UsageTriggers that trigger by this field in the UsageRecord. Must be one of: count , usage , or price as described in the UsageRecords documentation .",
            "type": "integer",
            "required": "required"
          }
        ]
      }
    },
    "/SIP/CredentialLists/CL32a3c": {
      "get": {
        "parameters": [
          {
            "in": "query",
            "name": "Password",
            "description": "The password will not be returned in the response.",
            "type": "integer",
            "required": "required"
          }
        ]
      }
    },
    "/Calls/FeedbackSummary": {
      "POST": {
        "parameters": [
          {
            "in": "query",
            "name": "StartDate",
            "description": "The first date for which feedback entries are included in this Feedback Summary, formatted as YYYY-MM-DD. All dates are in UTC.",
            "type": "integer",
            "required": "required"
          },
          {
            "in": "query",
            "name": "EndDate",
            "description": "The last date for which feedback entries are included in this Feedback Summary, formatted as YYYY-MM-DD. All dates are in UTC.",
            "type": "integer",
            "required": "required"
          },
          {
            "in": "query",
            "name": "AccountSid",
            "description": "The Account that reported the feedback entry.",
            "type": "integer",
            "required": "required"
          },
          {
            "in": "query",
            "name": "IncludeSubaccounts",
            "description": "true if the feedback summary includes subaccounts, false otherwise.",
            "type": "integer",
            "required": "required"
          },
          {
            "in": "query",
            "name": "Status",
            "description": "The status of the feedback summary can be queued, in-progress, completed, or failed.",
            "type": "integer",
            "required": "required"
          },
          {
            "in": "query",
            "name": "CallCount",
            "description": "The total number of calls.",
            "type": "integer",
            "required": "required"
          },
          {
            "in": "query",
            "name": "CallFeedbackCount",
            "description": "The total number of calls with a feedback entry.",
            "type": "integer",
            "required": "required"
          },
          {
            "in": "query",
            "name": "QualityScoreAverage",
            "description": "The average QualityScore of the feedback entries.",
            "type": "integer",
            "required": "required"
          },
          {
            "in": "query",
            "name": "QualityScoreMedian",
            "description": "The median QualityScore of the feedback entries.",
            "type": "integer",
            "required": "required"
          },
          {
            "in": "query",
            "name": "QualityScoreStandardDeviation",
            "description": "The standard deviation of the quality scores.",
            "type": "integer",
            "required": "required"
          },
          {
            "in": "query",
            "name": "Issues",
            "description": "A list of all the issues experienced. The list includes the issue name, the number of occurrences and percentage of calls that experienced this issue.",
            "type": "integer",
            "required": "required"
          }
        ]
      }
    },
    "/AuthorizedConnectApps/CN472": {
      "get": {}
    },
    "/IncomingPhoneNumbers/PN2a07": {
      "POST": {
        "parameters": [
          {
            "in": "query",
            "name": "PhoneNumber",
            "description": "Only show the incoming phone number resources that match this pattern. You can specify partial numbers and use '*' as a wildcard for any digit.",
            "type": "integer",
            "required": "required"
          },
          {
            "in": "query",
            "name": "FriendlyName",
            "description": "Only show the incoming phone number resources with friendly names that exactly match this name.",
            "type": "integer",
            "required": "required"
          },
          {
            "in": "query",
            "name": "Beta",
            "description": "Include phone numbers new to the Twilio platform. Possible values are either true or false . Default is true .",
            "type": "integer",
            "required": "required"
          }
        ]
      },
      "get": {
        "parameters": [
          {
            "in": "query",
            "name": "ApiVersion",
            "description": "Calls to this phone number will start a new TwiML session with this API version. Either 2010-04-01 or 2008-08-01 .",
            "type": "integer",
            "required": "required"
          },
          {
            "in": "query",
            "name": "VoiceUrl",
            "description": "The URL that Twilio should request when somebody dials the phone number. The VoiceURL will no longer be used if a VoiceApplicationSid or a TrunkSid is set.",
            "type": "integer",
            "required": "required"
          },
          {
            "in": "query",
            "name": "VoiceMethod",
            "description": "The HTTP method that should be used to request the VoiceUrl . Either GET or POST .",
            "type": "integer",
            "required": "required"
          },
          {
            "in": "query",
            "name": "VoiceFallbackUrl",
            "description": "A URL that Twilio will request if an error occurs requesting or executing the TwiML defined by VoiceUrl .",
            "type": "integer",
            "required": "required"
          },
          {
            "in": "query",
            "name": "VoiceFallbackMethod",
            "description": "The HTTP method that should be used to request the VoiceFallbackUrl . Either GET or POST .",
            "type": "integer",
            "required": "required"
          },
          {
            "in": "query",
            "name": "StatusCallback",
            "description": "The URL that Twilio will request to pass status parameters (such as call ended) to your application.",
            "type": "integer",
            "required": "required"
          },
          {
            "in": "query",
            "name": "StatusCallbackMethod",
            "description": "The HTTP method Twilio will use to make requests to the StatusCallback URL. Either GET or POST .",
            "type": "integer",
            "required": "required"
          },
          {
            "in": "query",
            "name": "VoiceCallerIdLookup",
            "description": "Do a lookup of a caller's name from the CNAM database and post it to your app. Either true or false .",
            "type": "integer",
            "required": "required"
          },
          {
            "in": "query",
            "name": "VoiceApplicationSid",
            "description": "The 34 character sid of the application Twilio should use to handle phone calls to this number. If a VoiceApplicationSid is present, Twilio will ignore all of the voice urls above and use those set on the application instead. Setting a VoiceApplicationSid will automatically delete your TrunkSid and vice versa.",
            "type": "integer",
            "required": "required"
          },
          {
            "in": "query",
            "name": "TrunkSid",
            "description": "The 34 character sid of the Trunk Twilio should use to handle phone calls to this number. If a TrunkSid is present, Twilio will ignore all of the voice urls and voice applications above and use those set on the Trunk. Setting a TrunkSid will automatically delete your VoiceApplicationSid and vice versa.",
            "type": "integer",
            "required": "required"
          },
          {
            "in": "query",
            "name": "SmsUrl",
            "description": "The URL that Twilio should request when somebody sends an SMS to the new phone number.",
            "type": "integer",
            "required": "required"
          },
          {
            "in": "query",
            "name": "SmsMethod",
            "description": "The HTTP method that should be used to request the SmsUrl . Either GET or POST .",
            "type": "integer",
            "required": "required"
          },
          {
            "in": "query",
            "name": "SmsFallbackUrl",
            "description": "A URL that Twilio will request if an error occurs requesting or executing the TwiML defined by SmsUrl .",
            "type": "integer",
            "required": "required"
          },
          {
            "in": "query",
            "name": "SmsFallbackMethod",
            "description": "The HTTP method that should be used to request the SmsFallbackUrl . Either GET or POST .",
            "type": "integer",
            "required": "required"
          },
          {
            "in": "query",
            "name": "SmsApplicationSid",
            "description": "The 34 character sid of the application Twilio should use to handle SMSs sent to this number. If a SmsApplicationSid is present, Twilio will ignore all of the SMS urls above and use those set on the application instead.",
            "type": "integer",
            "required": "required"
          },
          {
            "in": "query",
            "name": "AccountSid",
            "description": "The unique 34 character id of the account to which you wish to transfer this phone number. See Exchanging Numbers Between Subaccounts .",
            "type": "integer",
            "required": "required"
          }
        ]
      }
    },
    "https://dundermifflin.example.com/twilio/app.php\"": {
      "POST": {
        "parameters": []
      }
    },
    "/Transcriptions/TR8c61027b70": {
      "DELETE": {}
    },
    "/AvailablePhoneNumbers/US/Lo": {
      "post": {
        "parameters": [
          {
            "in": "query",
            "name": "AreaCode",
            "description": "Find phone numbers in the specified area code.",
            "type": "integer",
            "required": "required"
          },
          {
            "in": "query",
            "name": "Contains",
            "description": "A pattern to match phone numbers on. Valid characters are '*' and [0-9a-zA-Z] . The '*' character will match any single digit. See Example 2 below.",
            "type": "integer",
            "required": "required"
          },
          {
            "in": "query",
            "name": "SmsEnabled",
            "description": "This indicates whether the phone numbers can receive text messages. Possible values are true or false .",
            "type": "integer",
            "required": "required"
          },
          {
            "in": "query",
            "name": "MmsEnabled",
            "description": "This indicates whether the phone numbers can receive MMS messages. Possible values are true or false .",
            "type": "integer",
            "required": "required"
          },
          {
            "in": "query",
            "name": "VoiceEnabled",
            "description": "This indicates whether the phone numbers can receive calls. Possible values are true or false .",
            "type": "integer",
            "required": "required"
          },
          {
            "in": "query",
            "name": "ExcludeAllAddressRequired",
            "description": "Indicates whether the response includes phone numbers which require any Address . Possible values are true or false . If not specified, the default is false , and results could include phone numbers with an Address required.",
            "type": "integer",
            "required": "required"
          },
          {
            "in": "query",
            "name": "ExcludeLocalAddressRequired",
            "description": "Indicates whether the response includes phone numbers which require a local Address . Possible values are true or false . If not specified, the default is false , and results could include phone numbers with a local Address required.",
            "type": "integer",
            "required": "required"
          },
          {
            "in": "query",
            "name": "ExcludeForeignAddressRequired",
            "description": "Indicates whether the response includes phone numbers which require a foreign Address . Possible values are true or false . If not specified, the default is false , and results could include phone numbers with a foreign Address required.",
            "type": "integer",
            "required": "required"
          },
          {
            "in": "query",
            "name": "Beta",
            "description": "Include phone numbers new to the Twilio platform. Possible values are either true or false . Default is true .",
            "type": "integer",
            "required": "required"
          }
        ]
      },
      "put": {
        "parameters": [
          {
            "in": "query",
            "name": "NearNumber",
            "description": "Given a phone number, find a geographically close number within Distance miles. Distance defaults to 25 miles.",
            "type": "integer",
            "required": "required"
          },
          {
            "in": "query",
            "name": "NearLatLong",
            "description": "Given a latitude/longitude pair lat,long find geographically close numbers within Distance miles.",
            "type": "integer",
            "required": "required"
          },
          {
            "in": "query",
            "name": "Distance",
            "description": "Specifies the search radius for a Near- query in miles. If not specified this defaults to 25 miles. Maximum searchable distance is 500 miles.",
            "type": "integer",
            "required": "required"
          },
          {
            "in": "query",
            "name": "InPostalCode",
            "description": "Limit results to a particular postal code. Given a phone number, search within the same postal code as that number.",
            "type": "integer",
            "required": "required"
          },
          {
            "in": "query",
            "name": "InRegion",
            "description": "Limit results to a particular region (i.e. State/Province). Given a phone number, search within the same Region as that number.",
            "type": "integer",
            "required": "required"
          },
          {
            "in": "query",
            "name": "InRateCenter",
            "description": "Limit results to a specific rate center, or given a phone number search within the same rate center as that number. Requires InLata to be set as well.",
            "type": "integer",
            "required": "required"
          },
          {
            "in": "query",
            "name": "InLata",
            "description": "Limit results to a specific Local access and transport area ( LATA ). Given a phone number, search within the same LATA as that number.",
            "type": "integer",
            "required": "required"
          }
        ]
      }
    },
    "/Usage/Triggers/UT33c6aeeba3": {
      "get": {
        "parameters": [
          {
            "in": "query",
            "name": "Twilio will make a request to this url when the trigger fires.",
            "description": "Twilio will make a request to this url when the trigger fires.",
            "type": "integer",
            "required": "required"
          },
          {
            "in": "query",
            "name": "The HTTP method Twilio will use when making a request to the CallbackUrl. GET or POST .",
            "description": "The HTTP method Twilio will use when making a request to the CallbackUrl. GET or POST .",
            "type": "integer",
            "required": "required"
          }
        ]
      }
    },
    "/Keys": {
      "get": {
        "parameters": []
      }
    },
    "/Addresses": {
      "get": {
        "parameters": [
          {
            "in": "query",
            "name": "The number and street address where you or your customer is located.",
            "description": "The number and street address where you or your customer is located.",
            "type": "integer",
            "required": "required"
          },
          {
            "in": "query",
            "name": "The city in which you or your customer is located.",
            "description": "The city in which you or your customer is located.",
            "type": "integer",
            "required": "required"
          },
          {
            "in": "query",
            "name": "The state or region in which you or your customer is located.",
            "description": "The state or region in which you or your customer is located.",
            "type": "integer",
            "required": "required"
          },
          {
            "in": "query",
            "name": "The postal code in which you or your customer is located.",
            "description": "The postal code in which you or your customer is located.",
            "type": "integer",
            "required": "required"
          },
          {
            "in": "query",
            "name": "The ISO country code of your or your customer's address.",
            "description": "The ISO country code of your or your customer's address.",
            "type": "integer",
            "required": "required"
          }
        ]
      }
    },
    "/Conferences/CFbbe4632a3c497": {
      "DELETE": {
        "parameters": [
          {
            "in": "query",
            "name": "Muted",
            "description": "Only show participants that are muted or unmuted. Either true or false .",
            "type": "integer",
            "required": "required"
          },
          {
            "in": "query",
            "name": "Hold",
            "description": "Only show participants that are held or unheld. Either true or false .",
            "type": "integer",
            "required": "required"
          }
        ]
      },
      "put": {
        "parameters": [
          {
            "in": "query",
            "name": "Hold",
            "description": "Specifying true will hold the participant, while false will un-hold.",
            "type": "integer",
            "required": "required"
          },
          {
            "in": "query",
            "name": "HoldUrl",
            "description": "The 'HoldUrl' attribute lets you specify a URL for music that plays when a participant is held. The URL may be an MP3, a WAV or a TwiML document that uses <Play> <Say> or <Redirect>.",
            "type": "integer",
            "required": "required"
          },
          {
            "in": "query",
            "name": "HoldMethod",
            "description": "Specify GET or POST, defaults to POST",
            "type": "integer",
            "required": "required"
          },
          {
            "in": "query",
            "name": "Muted",
            "description": "Specifying true will mute the participant, while false will un-mute. Anything other than true or false is interpreted as false .",
            "type": "integer",
            "required": "required"
          }
        ]
      }
    },
    "/Addresses/AD2a0747eba6abf96": {
      "POST": {
        "parameters": [
          {
            "in": "query",
            "name": "Only return the Address resources with friendly names that exactly match this name.",
            "description": "Only return the Address resources with friendly names that exactly match this name.",
            "type": "integer",
            "required": "required"
          },
          {
            "in": "query",
            "name": "Only return the Address resources in this country.",
            "description": "Only return the Address resources in this country.",
            "type": "integer",
            "required": "required"
          }
        ]
      },
      "get": {
        "parameters": [
          {
            "in": "query",
            "name": "Sid",
            "description": "A 34 character string that uniquely identifies this address.",
            "type": "integer",
            "required": "required"
          },
          {
            "in": "query",
            "name": "AccountSid",
            "description": "The unique id of the Account responsible for this address.",
            "type": "integer",
            "required": "required"
          },
          {
            "in": "query",
            "name": "FriendlyName",
            "description": "A human-readable description of the address. Maximum 64 characters.",
            "type": "integer",
            "required": "required"
          },
          {
            "in": "query",
            "name": "CustomerName",
            "description": "Your name or business name, or that of your customer.",
            "type": "integer",
            "required": "required"
          },
          {
            "in": "query",
            "name": "Street",
            "description": "The number and street address where you or your customer is located.",
            "type": "integer",
            "required": "required"
          },
          {
            "in": "query",
            "name": "City",
            "description": "The city in which you or your customer is located.",
            "type": "integer",
            "required": "required"
          },
          {
            "in": "query",
            "name": "Region",
            "description": "The state or region in which you or your customer is located.",
            "type": "integer",
            "required": "required"
          },
          {
            "in": "query",
            "name": "PostalCode",
            "description": "The postal code in which you or your customer is located.",
            "type": "integer",
            "required": "required"
          }
        ]
      }
    },
    "/AvailablePhoneNumbers/US/To": {
      "put": {
        "parameters": [
          {
            "in": "query",
            "name": "Contains",
            "description": "A pattern to match phone numbers on. Valid characters are '*' and [0-9a-zA-Z] . The '*' character will match any single digit. See Example 2 above.",
            "type": "integer",
            "required": "required"
          },
          {
            "in": "query",
            "name": "SmsEnabled",
            "description": "This indicates whether the phone numbers can receive text messages. Possible values are true or false .",
            "type": "integer",
            "required": "required"
          },
          {
            "in": "query",
            "name": "MmsEnabled",
            "description": "This indicates whether the phone numbers can receive MMS messages. Possible values are true or false .",
            "type": "integer",
            "required": "required"
          },
          {
            "in": "query",
            "name": "VoiceEnabled",
            "description": "This indicates whether the phone numbers can receive calls. Possible values are true or false .",
            "type": "integer",
            "required": "required"
          },
          {
            "in": "query",
            "name": "ExcludeAllAddressRequired",
            "description": "Indicates whether the response includes phone numbers which require any Address . Possible values are true or false . If not specified, the default is false , and results could include phone numbers with an Address required.",
            "type": "integer",
            "required": "required"
          },
          {
            "in": "query",
            "name": "ExcludeLocalAddressRequired",
            "description": "Indicates whether the response includes phone numbers which require a local Address . Possible values are true or false . If not specified, the default is false , and results could include phone numbers with a local Address required.",
            "type": "integer",
            "required": "required"
          },
          {
            "in": "query",
            "name": "ExcludeForeignAddressRequired",
            "description": "Indicates whether the response includes phone numbers which require a foreign Address . Possible values are true or false . If not specified, the default is false , and results could include phone numbers with a foreign Address required.",
            "type": "integer",
            "required": "required"
          },
          {
            "in": "query",
            "name": "Beta",
            "description": "Include phone numbers new to the Twilio platform. Possible values are either true or false . Default is true .",
            "type": "integer",
            "required": "required"
          }
        ]
      }
    },
    "/Messages/MM800f449d0399ed01": {
      "DELETE": {
        "parameters": [
          {
            "in": "query",
            "name": "DateCreated",
            "description": "Only show media created on the given date. Should be formatted as YYYY-MM-DD . You can also specify inequality, such as DateCreated<=YYYY-MM-DD for media generated at or before midnight on a date, and DateCreated>=YYYY-MM-DD for media generated at or after midnight on a date.",
            "type": "integer",
            "required": "required"
          }
        ]
      },
      "POST": {
        "parameters": [
          {
            "in": "query",
            "name": "To",
            "description": "Only show messages to this phone number.",
            "type": "integer",
            "required": "required"
          },
          {
            "in": "query",
            "name": "From",
            "description": "Only show messages from this phone number or alphanumeric sender ID.",
            "type": "integer",
            "required": "required"
          },
          {
            "in": "query",
            "name": "DateSent",
            "description": "Only show messages sent on this date (in GMT format), given as YYYY-MM-DD . Example: DateSent=2009-07-06 . You can also specify inequality, such as DateSent<=YYYY-MM-DD for messages that were sent on or before midnight on a date, and DateSent>=YYYY-MM-DD for messages sent on or after midnight on a date.",
            "type": "integer",
            "required": "required"
          }
        ]
      }
    },
    "/Keys/SK2a0747eba6abf96b7e3c": {
      "get": {
        "parameters": []
      }
    }
  },
  "host": "api.twilio.com",
  "schemes": [
    "https"
  ],
  "swagger": "2.0",
  "info": "This is the information of the API"
}