{
  "basePath": "/<",
  "paths": {
    "http%3A%2F%2Fexample.com%": {
      "POST": {
        "parameters": [
          {
            "in": "query",
            "name": "\nachievement\n\nThe",
            "description": "URL of an Open Graph Achievement object. This URL should contain the tags necessary to describe an Achievement object . This field is required.\n\nstring\n",
            "type": "integer",
            "required": "required"
          },
          {
            "in": "query",
            "name": "display_order\n\nOrder",
            "description": "of the achievement when shown in any achievement stories UI. A display order of 100 is displayed in the UI before 200. Values should be unique and incremented in the correct order for your achievements.\n\nint\n",
            "type": "integer",
            "required": "required"
          }
        ]
      }
    },
    "https://developers.google.com/streetview/spherical-metadata": {
      "post": {
        "parameters": [
          {
            "in": "query",
            "name": "100",
            "description": "Invalid parameter",
            "type": "integer",
            "required": "required"
          },
          {
            "in": "query",
            "name": "368",
            "description": "The action attempted has been deemed abusive or is otherwise disallowed",
            "type": "integer",
            "required": "required"
          },
          {
            "in": "query",
            "name": "240",
            "description": "Desktop applications cannot call this function for other users",
            "type": "integer",
            "required": "required"
          },
          {
            "in": "query",
            "name": "2010",
            "description": "Photos calls have been temporarily disabled for this application",
            "type": "integer",
            "required": "required"
          },
          {
            "in": "query",
            "name": "122",
            "description": "Invalid vault image id",
            "type": "integer",
            "required": "required"
          },
          {
            "in": "query",
            "name": "123",
            "description": "Invalid sync object uuid",
            "type": "integer",
            "required": "required"
          },
          {
            "in": "query",
            "name": "120",
            "description": "Invalid album id",
            "type": "integer",
            "required": "required"
          },
          {
            "in": "query",
            "name": "121",
            "description": "Invalid photo id",
            "type": "integer",
            "required": "required"
          },
          {
            "in": "query",
            "name": "190",
            "description": "Invalid OAuth 2.0 Access Token",
            "type": "integer",
            "required": "required"
          },
          {
            "in": "query",
            "name": "200",
            "description": "Permissions error",
            "type": "integer",
            "required": "required"
          }
        ]
      },
      "POST": {}
    },
    "https://www.facebook.com/<POST_ID>": {
      "post": {
        "parameters": [
          {
            "in": "query",
            "name": "\nNo",
            "description": "optional image parameters\n\nImage is sourced from the contents of the Link\n",
            "type": "integer",
            "required": "required"
          },
          {
            "in": "query",
            "name": "picture",
            "description": "parameter supplied\n\nstring\n\nURL for the image\n\nImage is sourced from the URL supplied in picture\n",
            "type": "integer",
            "required": "required"
          },
          {
            "in": "query",
            "name": "thumbnail",
            "description": "parameter supplied\n\nfile\n\nImage file to be uploaded. Accepts .jpg .jpeg .gif or .png\n\nImage is sourced from the file uploaded in thumbnail\n",
            "type": "integer",
            "required": "required"
          }
        ]
      },
      "POST": {}
    },
    "user_id>/invitable_friends": {
      "DEL": {},
      "Del": {
        "parameters": [
          {
            "in": "query",
            "name": "height\ninteger\n\nThe",
            "description": "height\ninteger\n\nThe height of this picture in pixels.\n",
            "type": "integer",
            "required": "required"
          },
          {
            "in": "query",
            "name": "redirect\nboolean\nDefault",
            "description": "value: true\n\nBy default the picture edge will return a picture instead of a JSON response. If you want the picture edge to return JSON that describes the image set redirect=0 when you make the request.\n",
            "type": "integer",
            "required": "required"
          },
          {
            "in": "query",
            "name": "type\nenum{small,",
            "description": "normal, album, large, square}\n\nThe size of this picture. It can be one of the following values: small, normal, large, square.\n",
            "type": "integer",
            "required": "required"
          },
          {
            "in": "query",
            "name": "width\ninteger\n\nThe",
            "description": "width\ninteger\n\nThe width of this picture in pixels.\n",
            "type": "integer",
            "required": "required"
          }
        ]
      }
    },
    "https://developers.facebook.com/docs/graph-api/reference/insights)": {
      "DEL": {},
      "Del": {
        "parameters": [
          {
            "in": "query",
            "name": "100",
            "description": "Invalid parameter",
            "type": "integer",
            "required": "required"
          },
          {
            "in": "query",
            "name": "3001",
            "description": "Invalid query",
            "type": "integer",
            "required": "required"
          },
          {
            "in": "query",
            "name": "190",
            "description": "Invalid OAuth 2.0 Access Token",
            "type": "integer",
            "required": "required"
          }
        ]
      }
    },
    "video_id>": {
      "DEL": {
        "parameters": [
          {
            "in": "query",
            "name": "100",
            "description": "Invalid parameter",
            "type": "integer",
            "required": "required"
          },
          {
            "in": "query",
            "name": "200",
            "description": "Permissions error",
            "type": "integer",
            "required": "required"
          }
        ]
      }
    }
  },
  "produces": "application/json",
  "host": "graph.facebook.com",
  "schemes": [
    "https"
  ],
  "swagger": "2.0",
  "info": "This is the information of the API"
}