{
  "paths": {
    "http://yourlink.com/object.l3d\",": {
      "GET": {}
    },
    "http://m.layar.com/open/<layername>": {
      "DELETE": {},
      "delete": {
        "parameters": [
          {
            "in": "query",
            "name": "title",
            "description": "mandatory string Treasure hunt Title to show with the shared message",
            "type": "integer",
            "required": "required"
          },
          {
            "in": "query",
            "name": "type",
            "description": "mandatory string message Determines if the action should trigger sharing a message or a screenshot. use \"message\" to share a message.",
            "type": "integer",
            "required": "required"
          },
          {
            "in": "query",
            "name": "link",
            "description": "optional url http://developer.com/scoreboard/user This link is attached to the title parameter. It can be linked to a web page which shows more information about shared message.",
            "type": "integer",
            "required": "required"
          },
          {
            "in": "query",
            "name": "icon",
            "description": "optional url http://developer.com/image.png Places this icon next to a status update on Facebook. If not provided, the layer's icon (defined under Listing & indexing tab of the layer editing page) will be used. The recommended icon size is 150x150. Not possible when sharing on Twitter.",
            "type": "integer",
            "required": "required"
          },
          {
            "in": "query",
            "name": "description",
            "description": "optional string Find more treasures with this layer! Text that will show when the user shares their status update. This text is determined by the developer and cannot be changed by the user.",
            "type": "integer",
            "required": "required"
          },
          {
            "in": "query",
            "name": "service",
            "description": "optional string(facebook, twitter, developer) facebook Introduced in API v7.0. This specifies a specific service this share action is meant to be used for. Only 'facebook', 'twitter' or 'developer' are supported at the moment. 'developer' works only if 'type' is 'screenshot' and is then pointing to the layer-defined developer URL for sharing screenshots .\nIf not specified, the user gets to choose which service to use. If specified, the user will directly use the defined service.",
            "type": "integer",
            "required": "required"
          }
        ]
      }
    },
    "http://layarapi.example.net/mylayer/getpoi": {
      "GET": {}
    },
    "http://mylayer.com/account": {
      "GET": {}
    }
  },
  "produces": "application/json",
  "swagger": "2.0",
  "info": "This is the information of the API"
}